[
  {
    "name": "Google",
    "status": "up",
    "time": 226,
    "uptimeDay": "100.00",
    "uptimeWeek": "0.00",
    "uptimeMonth": "0.00",
    "uptimeYear": "0.00"
  },
  {
    "name": "Wikipedia",
    "status": "up",
    "time": 272,
    "uptimeDay": "100.00",
    "uptimeWeek": "0.00",
    "uptimeMonth": "0.00",
    "uptimeYear": "0.00"
  },
  {
    "name": "Hacker News",
    "status": "up",
    "time": 216,
    "uptimeDay": "100.00",
    "uptimeWeek": "0.00",
    "uptimeMonth": "0.00",
    "uptimeYear": "0.00"
  },
  {
    "name": "abnzb",
    "status": "up",
    "time": 119,
    "uptimeDay": "100.00",
    "uptimeWeek": "0.00",
    "uptimeMonth": "0.00",
    "uptimeYear": "0.00"
  },
  {
    "name": "NZBGrabit",
    "status": "up",
    "time": 268,
    "uptimeDay": "100.00",
    "uptimeWeek": "0.00",
    "uptimeMonth": "0.00",
    "uptimeYear": "0.00"
  },
  {
    "name": "omgwtfnzbs",
    "status": "up",
    "time": 905,
    "uptimeDay": "44.44",
    "uptimeWeek": "0.00",
    "uptimeMonth": "0.00",
    "uptimeYear": "0.00"
  },
  {
    "name": "althub",
    "status": "up",
    "time": 560,
    "uptimeDay": "100.00",
    "uptimeWeek": "0.00",
    "uptimeMonth": "0.00",
    "uptimeYear": "0.00"
  },
  {
    "name": "binsearch",
    "status": "up",
    "time": 425,
    "uptimeDay": "100.00",
    "uptimeWeek": "0.00",
    "uptimeMonth": "0.00",
    "uptimeYear": "0.00"
  },
  {
    "name": "birds-of-binaries",
    "status": "up",
    "time": 745,
    "uptimeDay": "100.00",
    "uptimeWeek": "0.00",
    "uptimeMonth": "0.00",
    "uptimeYear": "0.00"
  },
  {
    "name": "bluraynzb",
    "status": "up",
    "time": 696,
    "uptimeDay": "100.00",
    "uptimeWeek": "0.00",
    "uptimeMonth": "0.00",
    "uptimeYear": "0.00"
  },
  {
    "name": "dognzb",
    "status": "up",
    "time": 1365,
    "uptimeDay": "85.19",
    "uptimeWeek": "0.00",
    "uptimeMonth": "0.00",
    "uptimeYear": "0.00"
  },
  {
    "name": "easy-leech",
    "status": "up",
    "time": 227,
    "uptimeDay": "100.00",
    "uptimeWeek": "0.00",
    "uptimeMonth": "0.00",
    "uptimeYear": "0.00"
  },
  {
    "name": "elitenzb",
    "status": "up",
    "time": 406,
    "uptimeDay": "100.00",
    "uptimeWeek": "0.00",
    "uptimeMonth": "0.00",
    "uptimeYear": "0.00"
  },
  {
    "name": "fileleechers",
    "status": "up",
    "time": 427,
    "uptimeDay": "100.00",
    "uptimeWeek": "0.00",
    "uptimeMonth": "0.00",
    "uptimeYear": "0.00"
  },
  {
    "name": "gingadaddy",
    "status": "up",
    "time": 557,
    "uptimeDay": "100.00",
    "uptimeWeek": "0.00",
    "uptimeMonth": "0.00",
    "uptimeYear": "0.00"
  },
  {
    "name": "headphones-vip",
    "status": "up",
    "time": 599,
    "uptimeDay": "100.00",
    "uptimeWeek": "0.00",
    "uptimeMonth": "0.00",
    "uptimeYear": "0.00"
  },
  {
    "name": "house-of-usenet",
    "status": "up",
    "time": 1034,
    "uptimeDay": "100.00",
    "uptimeWeek": "0.00",
    "uptimeMonth": "0.00",
    "uptimeYear": "0.00"
  },
  {
    "name": "miatrix",
    "status": "up",
    "time": 367,
    "uptimeDay": "100.00",
    "uptimeWeek": "0.00",
    "uptimeMonth": "0.00",
    "uptimeYear": "0.00"
  },
  {
    "name": "newzfinders",
    "status": "up",
    "time": 1518,
    "uptimeDay": "100.00",
    "uptimeWeek": "0.00",
    "uptimeMonth": "0.00",
    "uptimeYear": "0.00"
  },
  {
    "name": "ninjacentral",
    "status": "up",
    "time": 313,
    "uptimeDay": "100.00",
    "uptimeWeek": "0.00",
    "uptimeMonth": "0.00",
    "uptimeYear": "0.00"
  },
  {
    "name": "nzbking",
    "status": "up",
    "time": 363,
    "uptimeDay": "51.85",
    "uptimeWeek": "0.00",
    "uptimeMonth": "0.00",
    "uptimeYear": "0.00"
  },
  {
    "name": "nzbnation",
    "status": "up",
    "time": 460,
    "uptimeDay": "100.00",
    "uptimeWeek": "0.00",
    "uptimeMonth": "0.00",
    "uptimeYear": "0.00"
  },
  {
    "name": "NZB Su",
    "status": "up",
    "time": 273,
    "uptimeDay": "100.00",
    "uptimeWeek": "0.00",
    "uptimeMonth": "0.00",
    "uptimeYear": "0.00"
  },
  {
    "name": "nzbwolf",
    "status": "up",
    "time": 651,
    "uptimeDay": "100.00",
    "uptimeWeek": "0.00",
    "uptimeMonth": "0.00",
    "uptimeYear": "0.00"
  },
  {
    "name": "nzbcave",
    "status": "up",
    "time": 9596,
    "uptimeDay": "100.00",
    "uptimeWeek": "0.00",
    "uptimeMonth": "0.00",
    "uptimeYear": "0.00"
  },
  {
    "name": "nzbfinder",
    "status": "up",
    "time": 616,
    "uptimeDay": "100.00",
    "uptimeWeek": "0.00",
    "uptimeMonth": "0.00",
    "uptimeYear": "0.00"
  },
  {
    "name": "nzbforyou",
    "status": "up",
    "time": 1120,
    "uptimeDay": "100.00",
    "uptimeWeek": "0.00",
    "uptimeMonth": "0.00",
    "uptimeYear": "0.00"
  },
  {
    "name": "nzbgeek",
    "status": "up",
    "time": 1051,
    "uptimeDay": "100.00",
    "uptimeWeek": "0.00",
    "uptimeMonth": "0.00",
    "uptimeYear": "0.00"
  },
  {
    "name": "nzbhunter",
    "status": "up",
    "time": 665,
    "uptimeDay": "100.00",
    "uptimeWeek": "0.00",
    "uptimeMonth": "0.00",
    "uptimeYear": "0.00"
  },
  {
    "name": "nzbindex",
    "status": "up",
    "time": 561,
    "uptimeDay": "100.00",
    "uptimeWeek": "0.00",
    "uptimeMonth": "0.00",
    "uptimeYear": "0.00"
  },
  {
    "name": "NZBIndex.nl",
    "status": "up",
    "time": 1358,
    "uptimeDay": "100.00",
    "uptimeWeek": "0.00",
    "uptimeMonth": "0.00",
    "uptimeYear": "0.00"
  },
  {
    "name": "nzbnoob",
    "status": "up",
    "time": 699,
    "uptimeDay": "100.00",
    "uptimeWeek": "0.00",
    "uptimeMonth": "0.00",
    "uptimeYear": "0.00"
  },
  {
    "name": "nzbplanet",
    "status": "up",
    "time": 595,
    "uptimeDay": "100.00",
    "uptimeWeek": "0.00",
    "uptimeMonth": "0.00",
    "uptimeYear": "0.00"
  },
  {
    "name": "nzbstars",
    "status": "up",
    "time": 800,
    "uptimeDay": "100.00",
    "uptimeWeek": "0.00",
    "uptimeMonth": "0.00",
    "uptimeYear": "0.00"
  },
  {
    "name": "nzbxs",
    "status": "up",
    "time": 163,
    "uptimeDay": "100.00",
    "uptimeWeek": "0.00",
    "uptimeMonth": "0.00",
    "uptimeYear": "0.00"
  },
  {
    "name": "pourcesoir",
    "status": "up",
    "time": 874,
    "uptimeDay": "56.25",
    "uptimeWeek": "0.00",
    "uptimeMonth": "0.00",
    "uptimeYear": "0.00"
  },
  {
    "name": "scenenzbs",
    "status": "up",
    "time": 1385,
    "uptimeDay": "100.00",
    "uptimeWeek": "0.00",
    "uptimeMonth": "0.00",
    "uptimeYear": "0.00"
  },
  {
    "name": "Sky of Usenet",
    "status": "up",
    "time": 723,
    "uptimeDay": "100.00",
    "uptimeWeek": "0.00",
    "uptimeMonth": "0.00",
    "uptimeYear": "0.00"
  },
  {
    "name": "tabula-rasa",
    "status": "up",
    "time": 1348,
    "uptimeDay": "96.00",
    "uptimeWeek": "0.00",
    "uptimeMonth": "0.00",
    "uptimeYear": "0.00"
  },
  {
    "name": "The Hive",
    "status": "up",
    "time": 1548,
    "uptimeDay": "100.00",
    "uptimeWeek": "0.00",
    "uptimeMonth": "0.00",
    "uptimeYear": "0.00"
  },
  {
    "name": "Usenet Hub",
    "status": "up",
    "time": 1221,
    "uptimeDay": "100.00",
    "uptimeWeek": "0.00",
    "uptimeMonth": "0.00",
    "uptimeYear": "0.00"
  },
  {
    "name": "usenetcrawler",
    "status": "up",
    "time": 1002,
    "uptimeDay": "100.00",
    "uptimeWeek": "0.00",
    "uptimeMonth": "0.00",
    "uptimeYear": "0.00"
  },
  {
    "name": "usenethd",
    "status": "up",
    "time": 901,
    "uptimeDay": "100.00",
    "uptimeWeek": "0.00",
    "uptimeMonth": "0.00",
    "uptimeYear": "0.00"
  },
  {
    "name": "IPv6 test",
    "status": "up",
    "time": 80,
    "uptimeDay": "100.00",
    "uptimeWeek": "0.00",
    "uptimeMonth": "0.00",
    "uptimeYear": "0.00"
  },
  {
    "name": "binzb",
    "status": "up",
    "time": 77,
    "uptimeDay": "100.00",
    "uptimeWeek": "0.00",
    "uptimeMonth": "0.00",
    "uptimeYear": "0.00"
  },
  {
    "name": "brothers-of-usenet",
    "status": "up",
    "time": 60,
    "uptimeDay": "100.00",
    "uptimeWeek": "0.00",
    "uptimeMonth": "0.00",
    "uptimeYear": "0.00"
  },
  {
    "name": "FileSharingTalk",
    "status": "up",
    "time": 89,
    "uptimeDay": "100.00",
    "uptimeWeek": "0.00",
    "uptimeMonth": "0.00",
    "uptimeYear": "0.00"
  },
  {
    "name": "findnzb",
    "status": "up",
    "time": 60,
    "uptimeDay": "100.00",
    "uptimeWeek": "0.00",
    "uptimeMonth": "0.00",
    "uptimeYear": "0.00"
  },
  {
    "name": "digital-carnage",
    "status": "down",
    "time": 0,
    "uptimeDay": "0.00",
    "uptimeWeek": "0.00",
    "uptimeMonth": "0.00",
    "uptimeYear": "0.00"
  }
]